{
  "createdAt": "2026-07-21T18:13:49.519Z",
  "state": {
    "notes": [],
    "theme": "light",
    "events": [],
    "company": {
      "nif": "5000848280",
      "name": "UHOCHA - Comércio & Prestação de Serviços, Lda.",
      "location": "Lubango, Huíla"
    },
    "drivers": [
      {
        "bi": "005580774UE044",
        "id": "353e40d1-6b3f-4086-80d4-c83a15c0bada",
        "nif": "",
        "name": "MATEUS CÂNDIDO CATONDI",
        "files": {
          "bi": {
            "id": "31167bb2-9afd-4fa7-9e50-a486b1674537",
            "url": "/uploads/31167bb2-9afd-4fa7-9e50-a486b1674537.png",
            "originalName": "Adriano Vasco.PNG"
          },
          "photo": {
            "id": "94474dc4-3c9e-4546-b110-491a60e2c86f",
            "url": "/uploads/94474dc4-3c9e-4546-b110-491a60e2c86f.png",
            "size": 1885159,
            "category": "motorista-foto",
            "mimeType": "image/png",
            "storedName": "94474dc4-3c9e-4546-b110-491a60e2c86f.png",
            "uploadedAt": "2026-05-14T14:31:56.503Z",
            "originalName": "71E5B394-E045-4A31-8929-355EB6158F4D.png"
          }
        },
        "phone": "+244 929 590 955",
        "address": "Da nere, Talatona ",
        "biValid": "2035-07-04",
        "deposit": 0,
        "license": "LD-635139",
        "category": "B",
        "contacts": [],
        "createdAt": "2026-05-12T08:25:14.137Z",
        "updatedAt": "2026-05-14T14:31:56.698Z",
        "licenseValid": "2029-12-09",
        "contractStart": "2026-05-12",
        "addressLocation": {
          "latitude": -8.926534,
          "longitude": 13.213922,
          "capturedAt": "2026-05-14T14:31:56.698Z"
        }
      },
      {
        "bi": "004714022ME047",
        "id": "ca65619b-8949-4aa9-a110-17d211bda448",
        "nif": "004714022ME047",
        "name": "LUIS FRANÇA MANUEL ",
        "files": {
          "bi": {
            "id": "f1338037-c889-4a0f-9ea3-21cc1969378d",
            "url": "/uploads/f1338037-c889-4a0f-9ea3-21cc1969378d.png",
            "originalName": "Antonio Manuel.PNG"
          }
        },
        "phone": "+244 924 451 460",
        "address": "RUA 88 CASA Nº 58 ZONA 9 BAIRRO CASSEQUEL MAIANGA",
        "biValid": "2035-07-20",
        "deposit": 0,
        "license": "KM-64903",
        "category": "D",
        "contacts": [],
        "createdAt": "2026-05-12T08:25:14.143Z",
        "updatedAt": "2026-05-14T09:09:00.922Z",
        "licenseValid": "2039-02-12",
        "contractStart": "2026-05-14",
        "addressLocation": {
          "latitude": 0,
          "longitude": 0,
          "capturedAt": "2026-05-14T09:09:00.922Z"
        }
      },
      {
        "bi": "005292663LN043",
        "id": "0b9c6c48-c864-4f7b-a8da-d9f7a074a64b",
        "nif": "",
        "name": "CARLOS JORGE DOMINGOS",
        "files": {
          "bi": {
            "id": "aade1b4d-853a-4e2b-860e-5afb79fae206",
            "url": "/uploads/aade1b4d-853a-4e2b-860e-5afb79fae206.png",
            "originalName": "Carlos.PNG"
          },
          "photo": {
            "id": "178840ca-5e7b-4eef-8b64-fc7d4a5e390a",
            "url": "/uploads/178840ca-5e7b-4eef-8b64-fc7d4a5e390a.png",
            "size": 1931372,
            "category": "motorista-foto",
            "mimeType": "image/png",
            "storedName": "178840ca-5e7b-4eef-8b64-fc7d4a5e390a.png",
            "uploadedAt": "2026-05-14T14:30:51.169Z",
            "originalName": "507AA91E-F499-49D0-8F0E-C5BEA646879D.png"
          }
        },
        "phone": "",
        "address": "CASA S/Nº GAMEK MACON",
        "biValid": "2032-04-05",
        "deposit": 0,
        "license": "LN-18299",
        "category": "D",
        "contacts": [],
        "createdAt": "2026-05-12T08:25:14.149Z",
        "updatedAt": "2026-05-14T14:30:51.344Z",
        "licenseValid": "2039-05-07",
        "contractStart": "2026-05-12",
        "addressLocation": {
          "latitude": -8.882699,
          "longitude": 13.209432,
          "capturedAt": "2026-05-14T14:30:51.344Z"
        }
      },
      {
        "bi": "005329559ME043",
        "id": "95ade306-3c82-45da-9f23-b5a6f69be31f",
        "nif": "",
        "name": "JORGE VENTURA CANDA GONGA",
        "files": {
          "bi": {
            "id": "627d3c2b-3a5d-4845-a904-3a3a0adf9694",
            "url": "/uploads/627d3c2b-3a5d-4845-a904-3a3a0adf9694.png",
            "originalName": "Jorge Ventura.PNG"
          }
        },
        "phone": "",
        "address": "CASA S/Nº BAIRRO BENFICA, FLORESTA",
        "biValid": "2033-05-19",
        "deposit": 0,
        "license": "LD-387005",
        "category": "D",
        "contacts": [],
        "createdAt": "2026-05-12T08:25:14.154Z",
        "updatedAt": "2026-05-12T17:29:26.118Z",
        "licenseValid": "2037-08-06",
        "contractStart": "2026-05-12",
        "addressLocation": {
          "latitude": -8.994623,
          "longitude": 13.099355,
          "capturedAt": "2026-05-12T17:29:26.118Z"
        }
      },
      {
        "bi": "000659602LA037",
        "id": "95ed6e00-1406-46d0-b295-0a9b36098c79",
        "nif": "",
        "name": "JOSÉ CÂNDIDO PEREIRA",
        "files": {
          "bi": {
            "id": "7a35accf-5655-40bd-8caa-bfa833cbb719",
            "url": "/uploads/7a35accf-5655-40bd-8caa-bfa833cbb719.png",
            "originalName": "Josó Pereira.PNG"
          },
          "photo": {
            "id": "923ffcaf-333c-4d34-84db-df8633de8959",
            "url": "/uploads/923ffcaf-333c-4d34-84db-df8633de8959.png",
            "size": 1721231,
            "category": "motorista-foto",
            "mimeType": "image/png",
            "storedName": "923ffcaf-333c-4d34-84db-df8633de8959.png",
            "uploadedAt": "2026-05-14T14:32:47.416Z",
            "originalName": "83C2AC5B-FCF9-4FB6-B62D-0F78E39DA707.png"
          }
        },
        "phone": "",
        "address": "SALÃO DO REINO DAS TESTUMINHAS DE JOVA, CAZENGA, ANGOLA E CUBA",
        "biValid": "2033-12-27",
        "deposit": 0,
        "license": "",
        "category": "",
        "contacts": [],
        "createdAt": "2026-05-12T08:25:14.157Z",
        "updatedAt": "2026-05-14T14:32:47.652Z",
        "licenseValid": "",
        "contractStart": "2026-05-12",
        "addressLocation": {
          "latitude": -8.828985,
          "longitude": 13.29889,
          "capturedAt": "2026-05-14T14:32:47.652Z"
        }
      },
      {
        "bi": "",
        "id": "1a806c6d-b959-48f9-b6b0-6a90ac7508ef",
        "nif": "",
        "name": "Amaral ",
        "files": {},
        "phone": "",
        "address": "Ilha de Luanda",
        "biValid": "",
        "deposit": 0,
        "license": "",
        "category": "",
        "contacts": [],
        "createdAt": "2026-06-08T17:23:21.415Z",
        "updatedAt": "2026-06-08T17:23:21.415Z",
        "licenseValid": "",
        "contractStart": "2026-06-08",
        "addressLocation": {
          "latitude": -8.787789,
          "longitude": 13.230837,
          "capturedAt": "2026-06-08T17:23:21.415Z"
        }
      }
    ],
    "version": 1,
    "expenses": [],
    "payments": [
      {
        "id": "ba50829d-10b3-428d-be05-36f75793a07d",
        "dueAt": "2026-05-18T11:00:00.000Z",
        "notes": "",
        "proof": "",
        "amount": 130000,
        "paidAt": "2026-05-18T10:01:00.000Z",
        "driverId": "95ade306-3c82-45da-9f23-b5a6f69be31f",
        "createdAt": "2026-05-18T10:01:33.707Z",
        "vehicleId": "06c7ac8f-dc6d-427d-91e9-199be3dfc93a",
        "penaltyPaid": 100000
      }
    ],
    "settings": {
      "province": "Luanda",
      "trialDays": 30,
      "weeklyFee": 130000,
      "deliveryDay": 1,
      "deliveryHour": "12:00",
      "fineOffHours": 50000,
      "penaltyLate24": 5000,
      "penaltyLate72": 15000,
      "contractMonths": 12,
      "deductibleLimit": 80000,
      "returnDelayDaily": 30000,
      "maintenanceDayName": "Segunda-feira"
    },
    "vehicles": [
      {
        "id": "06c7ac8f-dc6d-427d-91e9-199be3dfc93a",
        "year": "2026",
        "brand": "SUZUKI",
        "color": "CINZENTA",
        "files": {
          "photo": {
            "id": "d3477c05-fcbf-4144-92d2-203660db3285",
            "url": "/uploads/d3477c05-fcbf-4144-92d2-203660db3285.png",
            "size": 2699656,
            "category": "viatura-foto",
            "mimeType": "image/png",
            "storedName": "d3477c05-fcbf-4144-92d2-203660db3285.png",
            "uploadedAt": "2026-05-14T14:33:31.877Z",
            "originalName": "A2313AF4-FB5C-4087-AB9C-328385977730.png"
          },
          "booklet": {
            "id": "43a4374b-d606-4057-9c7f-18ff9c423fef",
            "url": "/uploads/43a4374b-d606-4057-9c7f-18ff9c423fef.pdf",
            "originalName": "LDA-06-19-AM.pdf"
          }
        },
        "model": "S-PRESSO M/T",
        "plate": "LDA-06-19-AM",
        "status": "ativo",
        "booklet": "",
        "chassis": "MA3RFL61STA583148",
        "mileage": "",
        "driverId": "95ade306-3c82-45da-9f23-b5a6f69be31f",
        "createdAt": "2026-05-12T08:25:14.121Z",
        "updatedAt": "2026-05-14T14:33:32.057Z",
        "propertyTitle": "",
        "insurancePolicy": ""
      },
      {
        "id": "dadd3df0-507b-4d12-a79c-a333cf1e110e",
        "year": "2026",
        "brand": "SUZUKI",
        "color": "CINZENTA",
        "files": {
          "photo": {
            "id": "cf37a78c-d323-436a-8810-9186a5fbf95b",
            "url": "/uploads/cf37a78c-d323-436a-8810-9186a5fbf95b.png",
            "size": 2574704,
            "category": "viatura-foto",
            "mimeType": "image/png",
            "storedName": "cf37a78c-d323-436a-8810-9186a5fbf95b.png",
            "uploadedAt": "2026-05-14T09:26:30.022Z",
            "originalName": "34D2A600-77C6-4E02-B18C-0CA147ADFA4B.png"
          },
          "booklet": {
            "id": "de631329-aa21-454a-b5f2-c272cbd5bec7",
            "url": "/uploads/de631329-aa21-454a-b5f2-c272cbd5bec7.pdf",
            "originalName": "LDA-10-35-AM.pdf"
          }
        },
        "model": "S-PRESSO M/T",
        "plate": "LDA-10-35-AM",
        "status": "ativo",
        "booklet": "",
        "chassis": "MA3RFL61STA590529",
        "mileage": "",
        "driverId": "0b9c6c48-c864-4f7b-a8da-d9f7a074a64b",
        "createdAt": "2026-05-12T08:25:14.126Z",
        "updatedAt": "2026-05-14T09:26:30.188Z",
        "propertyTitle": "",
        "insurancePolicy": ""
      },
      {
        "id": "359c7107-a9da-49a0-a100-af851ccfaa42",
        "year": "2026",
        "brand": "SUZUKI",
        "color": "CINZENTA",
        "files": {
          "photo": {
            "id": "bdf922c1-ac23-44b8-b678-b7d9a89f6007",
            "url": "/uploads/bdf922c1-ac23-44b8-b678-b7d9a89f6007.png",
            "size": 2421652,
            "category": "viatura-foto",
            "mimeType": "image/png",
            "storedName": "bdf922c1-ac23-44b8-b678-b7d9a89f6007.png",
            "uploadedAt": "2026-05-14T09:23:30.513Z",
            "originalName": "01B2EF37-567F-4B7E-A0CE-4C8E4AE11115.png"
          },
          "booklet": {
            "id": "5e546b1f-0ccf-417e-8ecf-9f8706f1d5be",
            "url": "/uploads/5e546b1f-0ccf-417e-8ecf-9f8706f1d5be.pdf",
            "originalName": "LDA-93-38-AL.pdf"
          }
        },
        "model": "S-PRESSO M/T",
        "plate": "LDA-93-38-AL",
        "status": "ativo",
        "booklet": "",
        "chassis": "MA3RFL61STA596238",
        "mileage": "",
        "driverId": "ca65619b-8949-4aa9-a110-17d211bda448",
        "createdAt": "2026-05-12T08:25:14.128Z",
        "updatedAt": "2026-05-14T09:23:30.740Z",
        "propertyTitle": "",
        "insurancePolicy": ""
      },
      {
        "id": "e08dd1dc-4d3d-4bc2-8825-dec1ad072e64",
        "year": "2026",
        "brand": "SUZUKI",
        "color": "CINZENTA",
        "files": {
          "photo": {
            "id": "7f28fa9d-26cf-41f7-b6cb-3073e55b0718",
            "url": "/uploads/7f28fa9d-26cf-41f7-b6cb-3073e55b0718.png",
            "size": 2429431,
            "category": "viatura-foto",
            "mimeType": "image/png",
            "storedName": "7f28fa9d-26cf-41f7-b6cb-3073e55b0718.png",
            "uploadedAt": "2026-05-14T14:34:11.679Z",
            "originalName": "1C26FD68-3B15-4D96-856B-256D97A4D174.png"
          },
          "booklet": {
            "id": "8d2dbc99-41d8-4071-ac9a-85e8a8bd1ab3",
            "url": "/uploads/8d2dbc99-41d8-4071-ac9a-85e8a8bd1ab3.pdf",
            "originalName": "LDA-93-59-AL.pdf"
          }
        },
        "model": "S-PRESSO M/T",
        "plate": "LDA-93-59-AL",
        "status": "ativo",
        "booklet": "",
        "chassis": "MA3RFL61STA595605",
        "mileage": "",
        "driverId": "353e40d1-6b3f-4086-80d4-c83a15c0bada",
        "createdAt": "2026-05-12T08:25:14.131Z",
        "updatedAt": "2026-05-14T14:34:11.896Z",
        "propertyTitle": "",
        "insurancePolicy": ""
      },
      {
        "id": "f13e0f54-b338-4e3e-82e6-7e65315132a2",
        "year": "2026",
        "brand": "SUZUKI",
        "color": "BRANCA",
        "files": {
          "photo": {
            "id": "7bc0591e-3141-439e-a945-19e9d2e4f862",
            "url": "/uploads/7bc0591e-3141-439e-a945-19e9d2e4f862.png",
            "size": 2735534,
            "category": "viatura-foto",
            "mimeType": "image/png",
            "storedName": "7bc0591e-3141-439e-a945-19e9d2e4f862.png",
            "uploadedAt": "2026-05-14T09:31:18.975Z",
            "originalName": "CD4B79DA-C50C-495E-B8E7-610F6424E880.png"
          },
          "booklet": {
            "id": "28fe6bc3-8487-4498-99ed-5b980914535d",
            "url": "/uploads/28fe6bc3-8487-4498-99ed-5b980914535d.pdf",
            "originalName": "documentos_convertidos.pdf"
          }
        },
        "model": "S-PRESSO MT",
        "plate": "LDA-21-95-AM",
        "status": "ativo",
        "booklet": "",
        "chassis": "MA3RFL61STA590389",
        "mileage": "",
        "driverId": "95ed6e00-1406-46d0-b295-0a9b36098c79",
        "createdAt": "2026-05-12T09:18:08.369Z",
        "updatedAt": "2026-05-14T09:31:19.178Z",
        "propertyTitle": "",
        "insurancePolicy": ""
      },
      {
        "id": "2618f127-565c-40c4-ae80-9abd382c85a4",
        "year": "2026",
        "brand": "SUZUKI",
        "color": "BRANCA",
        "files": {},
        "model": "S-Presso Gasolina 1.0L MT",
        "plate": "LDA-24-42-AN",
        "status": "ativo",
        "booklet": "",
        "chassis": "MA3RFL61STA609299",
        "mileage": "",
        "driverId": "",
        "createdAt": "2026-07-21T17:12:10.833Z",
        "updatedAt": "2026-07-21T17:21:00.509Z",
        "propertyTitle": "",
        "insurancePolicy": ""
      },
      {
        "id": "9e1b96cd-b8b8-4b11-877c-58f58e06fe19",
        "year": "2026",
        "brand": "SUZUKI",
        "color": "CINZA PRATA",
        "files": {},
        "model": "S-Presso Gasolina 1.0L MT",
        "plate": "LDA-38-12-AN",
        "status": "ativo",
        "booklet": "",
        "chassis": "MA3RFL61STA607930",
        "mileage": "",
        "driverId": "",
        "createdAt": "2026-07-21T17:12:11.938Z",
        "updatedAt": "2026-07-21T17:12:11.938Z",
        "propertyTitle": "",
        "insurancePolicy": ""
      },
      {
        "id": "c02294ee-238b-42a8-ae6d-baa39aa16fb0",
        "year": "2026",
        "brand": "SUZUKI",
        "color": "BRANCA",
        "files": {},
        "model": "S-Presso Gasolina 1.0L MT",
        "plate": "LDA-24-51-AN",
        "status": "ativo",
        "booklet": "",
        "chassis": "MA3RFL61STA609017",
        "mileage": "",
        "driverId": "",
        "createdAt": "2026-07-21T17:12:12.860Z",
        "updatedAt": "2026-07-21T17:21:19.174Z",
        "propertyTitle": "",
        "insurancePolicy": ""
      },
      {
        "id": "abc5eda4-5a32-4225-a6cf-a5810bd4bb7c",
        "year": "2026",
        "brand": "SUZUKI",
        "color": "CINZA PRATA",
        "files": {},
        "model": "S-Presso Gasolina 1.0L MT",
        "plate": "LDA-37-34-AL",
        "status": "ativo",
        "booklet": "",
        "chassis": "MA3RFL61STA590340",
        "mileage": "",
        "driverId": "",
        "createdAt": "2026-07-21T17:12:13.680Z",
        "updatedAt": "2026-07-21T17:12:13.680Z",
        "propertyTitle": "",
        "insurancePolicy": ""
      },
      {
        "id": "a208841c-ff48-432d-ba29-38920765a377",
        "year": "2026",
        "brand": "SUZUKI",
        "color": "BRANCA",
        "files": {},
        "model": "S-Presso Gasolina 1.0L MT",
        "plate": "LDA-24-48-AN",
        "status": "ativo",
        "booklet": "",
        "chassis": "MA3RFL61STA608251",
        "mileage": "",
        "driverId": "",
        "createdAt": "2026-07-21T17:12:14.396Z",
        "updatedAt": "2026-07-21T17:21:34.775Z",
        "propertyTitle": "",
        "insurancePolicy": ""
      }
    ],
    "documents": [
      {
        "id": "16f0b0f8-927c-4903-ad5c-73d5355ef5ee",
        "file": {
          "id": "e3ead622-171b-4311-9a77-9d3b9ac4258f",
          "url": "/uploads/e3ead622-171b-4311-9a77-9d3b9ac4258f.jpg",
          "size": 106701,
          "category": "documento-vehicle",
          "mimeType": "image/jpeg",
          "storedName": "e3ead622-171b-4311-9a77-9d3b9ac4258f.jpg",
          "uploadedAt": "2026-07-21T17:12:10.892Z",
          "originalName": "2fcf49be-a45a-4646-ac77-e719ad0108a8.JPG"
        },
        "name": "Declaração",
        "notes": "Documento Sogepower de 2026-06-05. Combustível: GASOLINA. Chassis: MA3RFL61STA609299.",
        "scope": "vehicle",
        "number": "LDA-24-42-AN",
        "driverId": "",
        "createdAt": "2026-07-21T17:12:10.833Z",
        "expiresAt": "",
        "vehicleId": "2618f127-565c-40c4-ae80-9abd382c85a4"
      },
      {
        "id": "d8cf004a-9290-4978-b14b-22a396e3229d",
        "file": {
          "id": "b32590f4-7641-4464-ab86-f6df4a778724",
          "url": "/uploads/b32590f4-7641-4464-ab86-f6df4a778724.jpg",
          "size": 121591,
          "category": "documento-vehicle",
          "mimeType": "image/jpeg",
          "storedName": "b32590f4-7641-4464-ab86-f6df4a778724.jpg",
          "uploadedAt": "2026-07-21T17:12:11.964Z",
          "originalName": "00fd5e3c-1954-423c-a63e-071e049d548e.JPG"
        },
        "name": "Declaração",
        "notes": "Documento Sogepower de 2026-06-05. Combustível: GASOLINA. Chassis: MA3RFL61STA607930.",
        "scope": "vehicle",
        "number": "LDA-38-12-AN",
        "driverId": "",
        "createdAt": "2026-07-21T17:12:11.938Z",
        "expiresAt": "",
        "vehicleId": "9e1b96cd-b8b8-4b11-877c-58f58e06fe19"
      },
      {
        "id": "c4bbc438-2d1e-4751-9a1c-f68f48669d3e",
        "file": {
          "id": "0bbd56cf-b2eb-43dc-901d-b7e3aeb17577",
          "url": "/uploads/0bbd56cf-b2eb-43dc-901d-b7e3aeb17577.jpg",
          "size": 86232,
          "category": "documento-vehicle",
          "mimeType": "image/jpeg",
          "storedName": "0bbd56cf-b2eb-43dc-901d-b7e3aeb17577.jpg",
          "uploadedAt": "2026-07-21T17:12:12.803Z",
          "originalName": "f6c32097-34fd-4fd3-afae-1f79b271235f.JPG"
        },
        "name": "Declaração",
        "notes": "Documento Sogepower de 2026-06-05. Combustível: GASOLINA. Chassis: MA3RFL61STA609017.",
        "scope": "vehicle",
        "number": "LDA-24-51-AN",
        "driverId": "",
        "createdAt": "2026-07-21T17:12:12.860Z",
        "expiresAt": "",
        "vehicleId": "c02294ee-238b-42a8-ae6d-baa39aa16fb0"
      },
      {
        "id": "2fbe4fa2-b4a2-48ca-b485-72c53bbf9b09",
        "file": {
          "id": "0198cade-20ab-400b-a16f-db46f1ba4b78",
          "url": "/uploads/0198cade-20ab-400b-a16f-db46f1ba4b78.jpg",
          "size": 101479,
          "category": "documento-vehicle",
          "mimeType": "image/jpeg",
          "storedName": "0198cade-20ab-400b-a16f-db46f1ba4b78.jpg",
          "uploadedAt": "2026-07-21T17:12:13.744Z",
          "originalName": "ab69bf5c-92f6-427c-817c-3a265a335530.JPG"
        },
        "name": "Declaração",
        "notes": "Documento Sogepower de 2026-06-05. Combustível: GASOLINA. Chassis: MA3RFL61STA590340.",
        "scope": "vehicle",
        "number": "LDA-37-34-AL",
        "driverId": "",
        "createdAt": "2026-07-21T17:12:13.680Z",
        "expiresAt": "",
        "vehicleId": "abc5eda4-5a32-4225-a6cf-a5810bd4bb7c"
      },
      {
        "id": "c273b0e4-405e-47c3-9ed9-57b1f557cd06",
        "file": {
          "id": "b9d78709-9903-4a14-bd17-eba3879468f1",
          "url": "/uploads/b9d78709-9903-4a14-bd17-eba3879468f1.jpg",
          "size": 88198,
          "category": "documento-vehicle",
          "mimeType": "image/jpeg",
          "storedName": "b9d78709-9903-4a14-bd17-eba3879468f1.jpg",
          "uploadedAt": "2026-07-21T17:12:14.446Z",
          "originalName": "65cf57cf-dfeb-4904-bb46-0947d15ff724.JPG"
        },
        "name": "Declaração",
        "notes": "Documento Sogepower de 2026-06-05. Combustível: GASOLINA. Chassis: MA3RFL61STA608251.",
        "scope": "vehicle",
        "number": "LDA-24-48-AN",
        "driverId": "",
        "createdAt": "2026-07-21T17:12:14.396Z",
        "expiresAt": "",
        "vehicleId": "a208841c-ff48-432d-ba29-38920765a377"
      }
    ],
    "assignments": [
      {
        "id": "a30cb158-48d1-46a5-bf4b-8b5035329c62",
        "notes": "",
        "status": "ativo",
        "startAt": "2026-05-13T09:01:00.000Z",
        "driverId": "353e40d1-6b3f-4086-80d4-c83a15c0bada",
        "createdAt": "2026-05-14T09:02:06.076Z",
        "documents": {
          "booklet": true,
          "license": true,
          "insurance": true,
          "inspection": true
        },
        "fuelLevel": "cheio",
        "vehicleId": "e08dd1dc-4d3d-4bc2-8825-dec1ad072e64",
        "weeklyFee": 130000,
        "gpsConfirmed": true,
        "keysDelivered": true,
        "depositReceived": 0,
        "handoverMileage": ""
      },
      {
        "id": "b8071de6-d64d-4057-8855-631ab2b085b7",
        "notes": "",
        "status": "ativo",
        "startAt": "2026-05-13T09:04:00.000Z",
        "driverId": "95ed6e00-1406-46d0-b295-0a9b36098c79",
        "createdAt": "2026-05-14T09:04:38.269Z",
        "documents": {
          "booklet": true,
          "license": true,
          "insurance": true,
          "inspection": true
        },
        "fuelLevel": "cheio",
        "vehicleId": "f13e0f54-b338-4e3e-82e6-7e65315132a2",
        "weeklyFee": 130000,
        "gpsConfirmed": true,
        "keysDelivered": true,
        "depositReceived": 0,
        "handoverMileage": ""
      },
      {
        "id": "66ff7cfa-c630-4ba0-95b9-d5d22111dd67",
        "notes": "",
        "status": "ativo",
        "startAt": "2026-05-13T09:05:00.000Z",
        "driverId": "95ade306-3c82-45da-9f23-b5a6f69be31f",
        "createdAt": "2026-05-14T09:05:36.218Z",
        "documents": {
          "booklet": true,
          "license": true,
          "insurance": true,
          "inspection": true
        },
        "fuelLevel": "cheio",
        "vehicleId": "06c7ac8f-dc6d-427d-91e9-199be3dfc93a",
        "weeklyFee": 130000,
        "gpsConfirmed": true,
        "keysDelivered": true,
        "depositReceived": 0,
        "handoverMileage": ""
      },
      {
        "id": "496b8d38-cacf-4c3b-afd9-a91846c91e1f",
        "notes": "",
        "status": "ativo",
        "startAt": "2026-05-14T09:09:00.000Z",
        "driverId": "ca65619b-8949-4aa9-a110-17d211bda448",
        "createdAt": "2026-05-14T09:09:52.662Z",
        "documents": {
          "booklet": true,
          "license": true,
          "insurance": true,
          "inspection": true
        },
        "fuelLevel": "cheio",
        "vehicleId": "359c7107-a9da-49a0-a100-af851ccfaa42",
        "weeklyFee": 130000,
        "gpsConfirmed": true,
        "keysDelivered": true,
        "depositReceived": 0,
        "handoverMileage": ""
      },
      {
        "id": "0621ee1e-327d-432f-b471-1858186a822e",
        "notes": "",
        "status": "ativo",
        "startAt": "2026-05-14T09:10:00.000Z",
        "driverId": "0b9c6c48-c864-4f7b-a8da-d9f7a074a64b",
        "createdAt": "2026-05-14T09:10:34.419Z",
        "documents": {
          "booklet": true,
          "license": true,
          "insurance": true,
          "inspection": true
        },
        "fuelLevel": "cheio",
        "vehicleId": "dadd3df0-507b-4d12-a79c-a333cf1e110e",
        "weeklyFee": 130000,
        "gpsConfirmed": true,
        "keysDelivered": true,
        "depositReceived": 0,
        "handoverMileage": ""
      }
    ]
  },
  "updatedAt": "2026-07-21T17:30:44.343Z"
}